beauty/__init__.py
beauty/girl/__init__.py
beauty/girl/message.py
zjq_01-0.2.dist-info/METADATA
zjq_01-0.2.dist-info/WHEEL
zjq_01-0.2.dist-info/top_level.txt
zjq_01-0.2.dist-info/RECORD
