Metadata-Version: 2.1
Name: zjq-01
Version: 0.2
Summary: The members of this team are:钟佳棋，王思仁，黄楚洁
Home-page: UNKNOWN
Author: zjq
License: UNKNOWN
Platform: UNKNOWN
